{
  "labels": [
    {
      "x": 1008,
      "y": 534,
      "img": "51-3_text_Y"
    },
    {
      "x": 1035,
      "y": 504,
      "img": "51-3_text_Z"
    },
    {
      "x": 1086,
      "y": 560,
      "img": "51-3_text_Z1"
    },
    {
      "x": 1030,
      "y": 422,
      "img": "51-3_text_Z2"
    }
  ],
  "spots": [
    {
      "no": 50,
      "x": 998,
      "y": 521,
      "route": {
        "img": "route_50_1"
      },
      "line": {
        "x": -38,
        "y": -15
      },
      "offsets": {
        "10": {
          "x": 11,
          "y": -9
        }
      },
      "comment": {
        "type": "RT",
        "x": -4,
        "y": 21
      },
      "color": -1
    },
    {
      "no": 51,
      "x": 1064,
      "y": 480,
      "route": {
        "img": "route_51_1"
      },
      "line": {
        "x": -47,
        "y": 18
      },
      "landing": {
        "x": -44,
        "y": 3,
        "flag": 1,
        "type": 2
      },
      "comment": {
        "type": "LB",
        "x": -10,
        "y": 0
      },
      "color": 8
    },
    {
      "no": 52,
      "x": 1076,
      "y": 545,
      "route": {
        "img": "route_52_1"
      },
      "line": {
        "x": -23,
        "y": -40
      },
      "color": -1
    },
    {
      "no": 53,
      "x": 1076,
      "y": 412,
      "route": {
        "img": "route_53_1"
      },
      "line": {
        "x": -24,
        "y": 21
      },
      "color": -2
    }
  ],
  "airraids": [
    {
      "no": 50,
      "type": 1,
      "from": {
        "x": 1032,
        "y": 380
      },
      "to": {
        "x": 992,
        "y": 528
      }
    }
  ],
  "enemies": [
    {
      "no": 53,
      "x": 920,
      "y": 330,
      "img": "icon_1029"
    }
  ]
}
