{
  "labels": [
    {
      "x": 883,
      "y": 466,
      "img": "I"
    },
    {
      "x": 1012,
      "y": 472,
      "img": "J"
    },
    {
      "x": 973,
      "y": 330,
      "img": "K"
    },
    {
      "x": 1041,
      "y": 252,
      "img": "L"
    },
    {
      "x": 957,
      "y": 223,
      "img": "M"
    },
    {
      "x": 871,
      "y": 306,
      "img": "N"
    },
    {
      "x": 869,
      "y": 233,
      "img": "O"
    }
  ],
  "spots": [
    {
      "no": 22,
      "x": 873,
      "y": 453,
      "route": {
        "img": "route_22_1"
      },
      "line": {
        "x": -150,
        "y": -11
      },
      "color": -1
    },
    {
      "no": 23,
      "x": 1003,
      "y": 460,
      "route": {
        "img": "route_23_1"
      },
      "line": {
        "x": -106,
        "y": -9
      },
      "color": -1
    },
    {
      "no": 24,
      "x": 961,
      "y": 317,
      "route": {
        "img": "route_24_1"
      },
      "line": {
        "x": -171,
        "y": 1
      },
      "color": -1
    },
    {
      "no": 25,
      "x": 1031,
      "y": 239,
      "route": {
        "img": "route_25_1"
      },
      "line": {
        "x": -28,
        "y": 26
      },
      "offsets": {
        "10": {
          "x": 10,
          "y": -5
        }
      },
      "color": -1
    },
    {
      "no": 26,
      "x": 948,
      "y": 208,
      "route": {
        "img": "route_26_1"
      },
      "line": {
        "x": -38,
        "y": 21
      },
      "comment": {
        "type": "RT",
        "x": 0,
        "y": 0
      },
      "color": -1
    },
    {
      "no": 27,
      "x": 858,
      "y": 295,
      "route": {
        "img": "route_27_1"
      },
      "line": {
        "x": 18,
        "y": -72
      },
      "color": -1,
      "direction": "L"
    },
    {
      "no": 28,
      "x": 852,
      "y": 212,
      "route": {
        "img": "route_28_1"
      },
      "line": {
        "x": 29,
        "y": -13
      },
      "color": -2,
      "direction": "L"
    },
    {
      "no": 29,
      "x": 961,
      "y": 317,
      "route": {
        "img": "route_29_1"
      },
      "line": {
        "x": -40,
        "y": 12
      },
      "color": -1
    },
    {
      "no": 30,
      "x": 1031,
      "y": 239,
      "route": {
        "img": "route_30_1"
      },
      "line": {
        "x": -56,
        "y": 16
      },
      "offsets": {
        "10": {
          "x": 10,
          "y": -5
        }
      },
      "color": -1
    },
    {
      "no": 31,
      "x": 948,
      "y": 208,
      "route": {
        "img": "route_31_1"
      },
      "line": {
        "x": -1,
        "y": 26
      },
      "color": -1,
      "direction": "L"
    },
    {
      "no": 32,
      "x": 948,
      "y": 208,
      "route": {
        "img": "route_32_1"
      },
      "line": {
        "x": 24,
        "y": 6
      },
      "color": -1,
      "direction": "L"
    }
  ],
  "airraids": [
    {
      "no": 25,
      "type": 1,
      "from": {
        "x": 1020,
        "y": 138
      },
      "to": {
        "x": 1031,
        "y": 239
      }
    }
  ],
  "enemies": [
    {
      "no": 23,
      "x": 957,
      "y": 352,
      "img": "icon_531"
    },
    {
      "no": 24,
      "x": 958,
      "y": 227,
      "img": "icon_531"
    },
    {
      "no": 28,
      "x": 802,
      "y": 127,
      "img": "icon_1268"
    }
  ]
}
