{
  "bg": [
    "map56-4",
    {
      "name": "red",
      "img": "map56-4_red"
    },
    "map56-4_point"
  ],
  "spots": [
    {
      "no": 0,
      "x": 133,
      "y": 246
    },
    {
      "no": 1,
      "x": 207,
      "y": 272,
      "line": {
        "x": -37,
        "y": -13
      }
    },
    {
      "no": 2,
      "x": 244,
      "y": 351,
      "line": {
        "x": -29,
        "y": -59
      }
    },
    {
      "no": 3,
      "x": 279,
      "y": 428,
      "line": {
        "x": -28,
        "y": -57
      }
    },
    {
      "no": 4,
      "x": 356,
      "y": 197,
      "line": {
        "x": -133,
        "y": 5
      }
    },
    {
      "no": 5,
      "x": 328,
      "y": 292,
      "line": {
        "x": -67,
        "y": 10
      },
      "color": -1
    },
    {
      "no": 6,
      "x": 451,
      "y": 147,
      "line": {
        "x": -75,
        "y": 8
      },
      "color": -1
    },
    {
      "no": 7,
      "x": 465,
      "y": 358,
      "line": {
        "x": -198,
        "y": -9
      },
      "branch": {
        "type": "T",
        "x": 0,
        "y": -23,
        "beak": "straight"
      }
    },
    {
      "no": 8,
      "x": 535,
      "y": 283,
      "line": {
        "x": -159,
        "y": -78
      },
      "offsets": {
        "10": {
          "x": 8,
          "y": -10
        }
      },
      "color": -1
    },
    {
      "no": 9,
      "x": 630,
      "y": 434,
      "line": {
        "x": -141,
        "y": -68
      },
      "color": -1
    },
    {
      "no": 10,
      "x": 690,
      "y": 526,
      "line": {
        "x": -49,
        "y": -75
      },
      "offsets": {
        "10": {
          "x": 11,
          "y": 1
        }
      },
      "color": -1
    },
    {
      "no": 11,
      "x": 750,
      "y": 364,
      "line": {
        "x": -100,
        "y": 10
      }
    },
    {
      "no": 12,
      "x": 328,
      "y": 292,
      "line": {
        "x": 2,
        "y": -76
      },
      "color": -1,
      "direction": "L"
    },
    {
      "no": 13,
      "x": 465,
      "y": 358,
      "line": {
        "x": -164,
        "y": 7
      }
    },
    {
      "no": 14,
      "x": 465,
      "y": 358,
      "line": {
        "x": -117,
        "y": -59
      }
    },
    {
      "no": 15,
      "x": 535,
      "y": 283,
      "line": {
        "x": -73,
        "y": -116
      },
      "offsets": {
        "10": {
          "x": 8,
          "y": -10
        }
      },
      "color": -1
    },
    {
      "no": 16,
      "x": 535,
      "y": 283,
      "line": {
        "x": -57,
        "y": 13
      },
      "offsets": {
        "10": {
          "x": 8,
          "y": -10
        }
      },
      "color": -1
    },
    {
      "no": 17,
      "x": 630,
      "y": 434,
      "line": {
        "x": -83,
        "y": -132
      },
      "color": -1
    }
  ],
  "airbases": [
    {
      "phase": 0,
      "point": {
        "x": 164,
        "y": 193
      },
      "airbaseraids": [
        {
          "type": 0,
          "from": {
            "x": 401,
            "y": 261
          },
          "to": {
            "x": 161,
            "y": 198
          }
        },
        {
          "type": 0,
          "from": {
            "x": 421,
            "y": 286
          },
          "to": {
            "x": 161,
            "y": 228
          }
        }
      ]
    }
  ],
  "airraids": [
    {
      "no": 5,
      "type": 0,
      "from": {
        "x": 624,
        "y": 337
      },
      "to": {
        "x": 327,
        "y": 292
      }
    },
    {
      "no": 5,
      "type": 2,
      "from": {
        "x": 644,
        "y": 359
      },
      "to": {
        "x": 327,
        "y": 322
      }
    },
    {
      "no": 6,
      "type": 0,
      "from": {
        "x": 624,
        "y": 337
      },
      "to": {
        "x": 458,
        "y": 144
      }
    },
    {
      "no": 6,
      "type": 2,
      "from": {
        "x": 624,
        "y": 337
      },
      "to": {
        "x": 458,
        "y": 174
      }
    },
    {
      "no": 8,
      "type": 0,
      "from": {
        "x": 624,
        "y": 337
      },
      "to": {
        "x": 538,
        "y": 278
      }
    },
    {
      "no": 8,
      "type": 2,
      "from": {
        "x": 624,
        "y": 337
      },
      "to": {
        "x": 538,
        "y": 308
      }
    },
    {
      "no": 10,
      "type": 0,
      "from": {
        "x": 992,
        "y": 428
      },
      "to": {
        "x": 692,
        "y": 524
      }
    },
    {
      "no": 10,
      "type": 2,
      "from": {
        "x": 1011,
        "y": 446
      },
      "to": {
        "x": 692,
        "y": 554
      }
    }
  ],
  "enemies": [
    {
      "no": 2,
      "x": 205,
      "y": 329,
      "img": "icon_570"
    },
    {
      "no": 3,
      "x": 237,
      "y": 410,
      "img": "icon_570"
    },
    {
      "no": 4,
      "x": 320,
      "y": 169,
      "img": "icon_570"
    },
    {
      "no": 5,
      "x": 298,
      "y": 258,
      "img": "icon_570"
    },
    {
      "no": 6,
      "x": 397,
      "y": 96,
      "img": "icon_736"
    }
  ]
}
