{
  "labels": [
    {
      "x": 435,
      "y": 278,
      "img": "D"
    },
    {
      "x": 503,
      "y": 271,
      "img": "E"
    },
    {
      "x": 592,
      "y": 256,
      "img": "F"
    },
    {
      "x": 548,
      "y": 313,
      "img": "G"
    },
    {
      "x": 488,
      "y": 343,
      "img": "H"
    },
    {
      "x": 610,
      "y": 342,
      "img": "I"
    },
    {
      "x": 581,
      "y": 390,
      "img": "J"
    },
    {
      "x": 654,
      "y": 373,
      "img": "K"
    },
    {
      "x": 521,
      "y": 424,
      "img": "L"
    }
  ],
  "spots": [
    {
      "no": 10,
      "x": 424,
      "y": 267,
      "route": {
        "img": "route_10_1"
      },
      "line": {
        "x": 16,
        "y": -54
      },
      "color": -1,
      "direction": "L"
    },
    {
      "no": 11,
      "x": 503,
      "y": 254,
      "route": {
        "img": "route_11_1"
      },
      "line": {
        "x": -57,
        "y": -1
      },
      "color": -1
    },
    {
      "no": 12,
      "x": 583,
      "y": 242,
      "route": {
        "img": "route_12_1"
      },
      "line": {
        "x": -58,
        "y": -1
      },
      "offsets": {
        "10": {
          "x": 11,
          "y": -2
        }
      },
      "color": -1
    },
    {
      "no": 13,
      "x": 545,
      "y": 297,
      "route": {
        "img": "route_13_1"
      },
      "line": {
        "x": -29,
        "y": -28
      },
      "color": -1
    },
    {
      "no": 14,
      "x": 477,
      "y": 330,
      "route": {
        "img": "route_14_1"
      },
      "line": {
        "x": 21,
        "y": -28
      },
      "offsets": {
        "10": {
          "x": 10,
          "y": -8
        }
      },
      "color": -1,
      "direction": "L"
    },
    {
      "no": 15,
      "x": 599,
      "y": 327,
      "route": {
        "img": "route_15_1"
      },
      "line": {
        "x": -35,
        "y": -20
      },
      "offsets": {
        "10": {
          "x": 10,
          "y": -8
        }
      },
      "color": -1
    },
    {
      "no": 16,
      "x": 573,
      "y": 377,
      "route": {
        "img": "route_16_1"
      },
      "line": {
        "x": 7,
        "y": -32
      },
      "comment": {
        "type": "RT",
        "x": 0,
        "y": 0
      },
      "color": -1,
      "direction": "L"
    },
    {
      "no": 17,
      "x": 636,
      "y": 375,
      "route": {
        "img": "route_17_1"
      },
      "line": {
        "x": -44,
        "y": -10
      },
      "color": -1
    },
    {
      "no": 18,
      "x": 505,
      "y": 398,
      "route": {
        "img": "route_18_1"
      },
      "line": {
        "x": 22,
        "y": -25
      },
      "color": -2,
      "direction": "L"
    },
    {
      "no": 19,
      "x": 503,
      "y": 254,
      "route": {
        "img": "route_19_1"
      },
      "line": {
        "x": -9,
        "y": -34
      },
      "color": -1
    },
    {
      "no": 20,
      "x": 545,
      "y": 297,
      "route": {
        "img": "route_20_1"
      },
      "line": {
        "x": 12,
        "y": -34
      },
      "color": -1,
      "direction": "L"
    },
    {
      "no": 21,
      "x": 491,
      "y": 177,
      "color": -3
    }
  ],
  "airraids": [
    {
      "no": 10,
      "type": 1,
      "from": {
        "x": 298,
        "y": 401
      },
      "to": {
        "x": 424,
        "y": 272
      }
    },
    {
      "no": 12,
      "type": 3,
      "from": {
        "x": 485,
        "y": 442
      },
      "to": {
        "x": 583,
        "y": 242
      }
    },
    {
      "no": 12,
      "type": 2,
      "from": {
        "x": 467,
        "y": 462
      },
      "to": {
        "x": 583,
        "y": 261
      }
    },
    {
      "no": 14,
      "type": 2,
      "from": {
        "x": 382,
        "y": 410
      },
      "to": {
        "x": 477,
        "y": 360
      }
    },
    {
      "no": 14,
      "type": 1,
      "from": {
        "x": 360,
        "y": 390
      },
      "to": {
        "x": 477,
        "y": 330
      }
    },
    {
      "no": 15,
      "type": 3,
      "from": {
        "x": 485,
        "y": 442
      },
      "to": {
        "x": 599,
        "y": 327
      }
    },
    {
      "no": 15,
      "type": 2,
      "from": {
        "x": 467,
        "y": 462
      },
      "to": {
        "x": 599,
        "y": 341
      }
    }
  ],
  "enemies": [
    {
      "no": 10,
      "x": 365,
      "y": 226,
      "img": "icon_570"
    },
    {
      "no": 11,
      "x": 445,
      "y": 172,
      "img": "icon_805"
    },
    {
      "no": 16,
      "x": 511,
      "y": 261,
      "img": "icon_1216"
    },
    {
      "no": 18,
      "x": 458,
      "y": 241,
      "img": "icon_565"
    }
  ]
}
